apolo_api_client/__init__.py
apolo_api_client/client.py
apolo_api_client/jobs.py
apolo_api_client/py.typed
apolo_api_client-25.6.0.dist-info/LICENSE
apolo_api_client-25.6.0.dist-info/METADATA
apolo_api_client-25.6.0.dist-info/WHEEL
apolo_api_client-25.6.0.dist-info/RECORD
