Metadata-Version: 2.3
Name: apolo-api-client
Version: 25.6.0
Summary: Apolo internal client for Platform API
License: Proprietary
Author: apolo.us
Requires-Python: >=3.11,<4.0
Classifier: License :: Other/Proprietary License
Classifier: Programming Language :: Python :: 3
Classifier: Programming Language :: Python :: 3.11
Classifier: Programming Language :: Python :: 3.12
Classifier: Programming Language :: Python :: 3.13
Requires-Dist: aiohttp (>=3.8.1)
Requires-Dist: multidict (>=6)
Requires-Dist: python-dateutil (>=2.7.0)
Requires-Dist: yarl (>=1.10)
